{
	"name": "pipeline5",
	"properties": {
		"activities": [
			{
				"name": "Copy data1",
				"type": "Copy",
				"dependsOn": [],
				"policy": {
					"timeout": "7.00:00:00",
					"retry": 0,
					"retryIntervalInSeconds": 30,
					"secureOutput": false,
					"secureInput": false
				},
				"userProperties": [],
				"typeProperties": {
					"source": {
						"type": "AzureSqlSource",
						"sqlReaderQuery": {
							"value": "SELECT * FROM [SalesLT].[Product] WHERE PRODUCTID >= @{pipeline().parameters.ProductID}",
							"type": "Expression"
						}
					},
					"sink": {
						"type": "DelimitedTextSink",
						"storeSettings": {
							"type": "AzureDataLakeStoreWriteSettings",
							"copyBehavior": "FlattenHierarchy"
						},
						"formatSettings": {
							"type": "DelimitedTextWriteSettings",
							"quoteAllText": true,
							"fileExtension": ".txt"
						}
					},
					"enableStaging": false
				},
				"inputs": [
					{
						"referenceName": "AzureSqlTable1",
						"type": "DatasetReference"
					}
				],
				"outputs": [
					{
						"referenceName": "DelimitedText3",
						"type": "DatasetReference"
					}
				]
			}
		],
		"parameters": {
			"ProductID": {
				"type": "Int"
			}
		},
		"annotations": []
	}
}